camtrapdp/__init__.py
camtrapdp/deployments.py
camtrapdp/media.py
camtrapdp/observations.py
camtrapdp/test_deployment.py
camtrapdp/test_media.py
camtrapdp/test_observation.py
camtrapdp-0.1.0.dist-info/METADATA
camtrapdp-0.1.0.dist-info/WHEEL
camtrapdp-0.1.0.dist-info/top_level.txt
camtrapdp-0.1.0.dist-info/RECORD
