Metadata-Version: 2.1
Name: camtrapdp
Version: 0.1.0
Summary: Python library for working with the Camtrap Data Package format.
Author: Benjamin C. Evans
Project-URL: Homepage, https://github.com/bencevans/camtrap-dp-py
Project-URL: Issues, https://github.com/bencevans/camtrap-dp-py/issues
Classifier: Programming Language :: Python :: 3
Classifier: License :: OSI Approved :: MIT License
Classifier: Operating System :: OS Independent
Requires-Python: >=3.8
Requires-Dist: pandas <3,>2
